[
  {
    "id": "p1",
    "name": "NVIDIA GeForce RTX 4090 24GB Founders Edition",
    "category": "GPU",
    "brand": "NVIDIA",
    "price": 47500000,
    "oldPrice": 52000000,
    "image": "assets/images/products/rtx-4090.jpg",
    "icon": "🖼️",
    "specs": ["24GB VRAM", "Ada Lovelace", "450W"],
    "rating": "★★★★★",
    "ratingCount": 284,
    "crypto": "≈ 12.2 ETH / 0.71 BTC",
    "nft": true,
    "warranty": "36T",
    "badges": ["HOT", "NFT"]
  },
  {
    "id": "p2",
    "name": "AMD Ryzen 9 7950X3D 16-Core 3D V-Cache AM5",
    "category": "CPU",
    "brand": "AMD",
    "price": 19800000,
    "oldPrice": 0,
    "image": "assets/images/products/ryzen-7950x3d.jpg",
    "icon": "⚡",
    "specs": ["16C/32T", "128MB Cache", "AM5"],
    "rating": "★★★★★",
    "ratingCount": 192,
    "crypto": "≈ 5.1 ETH / 0.29 BTC",
    "nft": false,
    "warranty": "",
    "badges": ["MỚI"]
  },
  {
    "id": "p3",
    "name": "ASUS ROG Maximus Z790 Apex Encore DDR5 Wi-Fi 7",
    "category": "Mainboard",
    "brand": "ASUS",
    "price": 14400000,
    "oldPrice": 18000000,
    "image": "assets/images/products/rog-z790-apex.jpg",
    "icon": "🔩",
    "specs": ["DDR5", "PCIe 5.0", "Wi-Fi 7"],
    "rating": "★★★★☆",
    "ratingCount": 87,
    "crypto": "≈ 3.7 ETH",
    "nft": true,
    "warranty": "24T",
    "badges": ["-20%", "NFT"]
  },
  {
    "id": "p4",
    "name": "G.Skill Trident Z5 RGB DDR5-7200 CL34 64GB",
    "category": "RAM",
    "brand": "G.Skill",
    "price": 8900000,
    "oldPrice": 0,
    "image": "assets/images/products/gskill-z5-64gb.jpg",
    "icon": "💾",
    "specs": ["64GB Kit", "DDR5-7200", "RGB"],
    "rating": "★★★★★",
    "ratingCount": 156,
    "crypto": "≈ 2.3 ETH",
    "nft": false,
    "warranty": "",
    "badges": ["MỚI"]
  },
  {
    "id": "p5",
    "name": "Samsung 990 Pro 2TB M.2 PCIe 5.0 NVMe",
    "category": "SSD",
    "brand": "Samsung",
    "price": 4200000,
    "oldPrice": 5500000,
    "image": "assets/images/products/samsung-990-pro-2tb.jpg",
    "icon": "🌀",
    "specs": ["2TB", "PCIe 5.0", "14.7GB/s"],
    "rating": "★★★★★",
    "ratingCount": 341,
    "crypto": "≈ 1.08 ETH",
    "nft": false,
    "warranty": "",
    "badges": ["HOT"]
  }
]
